mcp_docker_server/__init__.py
mcp_docker_server/input_schemas.py
mcp_docker_server/log_analyzer.py
mcp_docker_server/output_schemas.py
mcp_docker_server/server.py
mcp_docker_server/settings.py
mcp_docker_server-0.0.7.dist-info/METADATA
mcp_docker_server-0.0.7.dist-info/WHEEL
mcp_docker_server-0.0.7.dist-info/entry_points.txt
mcp_docker_server-0.0.7.dist-info/licenses/LICENSE
mcp_docker_server-0.0.7.dist-info/RECORD
