Metadata-Version: 2.4
Name: mcp-docker-server
Version: 0.0.7
Summary: A Docker MCP Server
Project-URL: Repository, https://github.com/pnmice/mcp-docker-server
Project-URL: Issues, https://github.com/pnmice/mcp-docker-server/issues
Author-email: pnmice <pnmice@gmail.com>
License:                     GNU GENERAL PUBLIC LICENSE
License-File: LICENSE
Keywords: docker,mcp,server
Classifier: Development Status :: 4 - Beta
Classifier: Programming Language :: Python :: 3.11
Classifier: Programming Language :: Python :: 3.12
Requires-Python: >=3.11
Requires-Dist: docker>=7.1.0
Requires-Dist: mcp<2.0,>=1.1.0
Requires-Dist: paramiko<4.0,>=3.5.1
Requires-Dist: pydantic-settings>=2.2.0
Requires-Dist: pydantic>=2.6.0
Provides-Extra: dev
Requires-Dist: black>=24.0.0; extra == 'dev'
Requires-Dist: coverage>=7.0.0; extra == 'dev'
Requires-Dist: flake8>=7.0.0; extra == 'dev'
Requires-Dist: isort>=5.13.0; extra == 'dev'
Requires-Dist: mypy>=1.8.0; extra == 'dev'
Requires-Dist: pre-commit>=3.6.0; extra == 'dev'
Requires-Dist: pytest-asyncio>=0.23.0; extra == 'dev'
Requires-Dist: pytest-cov>=4.0.0; extra == 'dev'
Requires-Dist: pytest-docker>=3.1.0; extra == 'dev'
Requires-Dist: pytest-mock>=3.11.0; extra == 'dev'
Requires-Dist: pytest>=8.0.0; extra == 'dev'
Provides-Extra: lint
Requires-Dist: black>=24.0.0; extra == 'lint'
Requires-Dist: flake8>=7.0.0; extra == 'lint'
Requires-Dist: isort>=5.13.0; extra == 'lint'
Requires-Dist: mypy>=1.8.0; extra == 'lint'
Provides-Extra: test
Requires-Dist: coverage>=7.0.0; extra == 'test'
Requires-Dist: pytest-asyncio>=0.23.0; extra == 'test'
Requires-Dist: pytest-cov>=4.0.0; extra == 'test'
Requires-Dist: pytest-docker>=3.1.0; extra == 'test'
Requires-Dist: pytest-mock>=3.11.0; extra == 'test'
Requires-Dist: pytest>=8.0.0; extra == 'test'
